discordservices/__init__.py
discordservices/client.py
discordservices/errors.py
discordservices.py-0.0.2.dist-info/LICENSE
discordservices.py-0.0.2.dist-info/METADATA
discordservices.py-0.0.2.dist-info/WHEEL
discordservices.py-0.0.2.dist-info/top_level.txt
discordservices.py-0.0.2.dist-info/RECORD
