Metadata-Version: 2.1
Name: discordservices.py
Version: 0.0.2
Summary: A simple API wrapper for discordservices.net
Home-page: https://github.com/DiscordServices/discordservices.py
Author: mischievousdev
Author-email: miscdev.py@gmail.com
License: UNKNOWN
Platform: UNKNOWN
Classifier: Programming Language :: Python :: 3
Classifier: License :: OSI Approved :: MIT License
Classifier: Operating System :: OS Independent
Requires-Python: >=3.6
Requires-Dist: aiohttp (<3.7.0,>=3.3.0)
